bootstrap.py
buildout.cfg
license.txt
readme.txt
setup.py
stripogram/HTMLParser.py
stripogram/__init__.py
stripogram/html2safehtml.py
stripogram/html2text.py
stripogram/tests.py
stripogram.egg-info/PKG-INFO
stripogram.egg-info/SOURCES.txt
stripogram.egg-info/dependency_links.txt
stripogram.egg-info/not-zip-safe
stripogram.egg-info/top_level.txt