Metadata-Version: 1.0
Name: stripogram
Version: 1.5
Summary: Strip-o-Gram HTML Conversion Library
Home-page: https://sourceforge.net/projects/squishdot
Author: Chris Withers
Author-email: chris@simplistix.co.uk
License: UNKNOWN
Platform: UNKNOWN
